famp/__init__.py
famp/data_analysis.py
famp/exceptions.py
famp/modeling.py
famp/pdb_cleaner.py
famp/simulation.py
famp/scripts/dye_properties.csv
famp/scripts/linux/rosetta/linux_extract_pdb.sh
famp/scripts/mac_os/rosetta/mac_extract_pdb.sh
famp-0.0.6.dist-info/licenses/LICENSE
famp-0.0.6.dist-info/METADATA
famp-0.0.6.dist-info/WHEEL
famp-0.0.6.dist-info/top_level.txt
famp-0.0.6.dist-info/RECORD
