Metadata-Version: 2.4
Name: famp
Version: 0.0.6
Summary: FAMP - FRET assisted modeling Pipeline for RNA structures
Author-email: Felix Erichson <erichson@hs-mittweida.de>, Richard Börner <richard.boerner@hs-mittweida.de>
Maintainer-email: Felix Erichson <erichson@hs-mittweida.de>
License: GPL-3.0-or-later
Project-URL: Source, https://github.com/felixErichson/FAMP_rna
Keywords: integrative modeling,FRET,molecular dynemics,structure prediction,pipeline,RNA
Classifier: Programming Language :: Python
Classifier: License :: OSI Approved :: GNU General Public License v3 or later (GPLv3+)
Classifier: Operating System :: OS Independent
Classifier: Framework :: Jupyter
Classifier: Topic :: Scientific/Engineering :: Bio-Informatics
Requires-Python: >=3.10
License-File: LICENSE
Requires-Dist: numpy
Requires-Dist: pandas
Requires-Dist: MDAnalysis>=2.7
Requires-Dist: mdtraj>=1.9
Requires-Dist: fretraj>=0.2.11
Requires-Dist: matplotlib
Requires-Dist: seaborn
Requires-Dist: jupyter
Requires-Dist: ipykernel
Requires-Dist: scipy
Requires-Dist: lmfit
Provides-Extra: dev
Requires-Dist: bumpver; extra == "dev"
Requires-Dist: pytest; extra == "dev"
Requires-Dist: build; extra == "dev"
Requires-Dist: pytest-cov; extra == "dev"
Requires-Dist: pytest-mock; extra == "dev"
Provides-Extra: docs
Requires-Dist: jupyter-book; extra == "docs"
Requires-Dist: ipywidgets; extra == "docs"
Requires-Dist: matplotlib; extra == "docs"
Requires-Dist: seaborn; extra == "docs"
Dynamic: license-file
